{
  "policy": {
    "name": "query-noti",
    "resource": "huaweicloud.cts-notification-smn",
    "filters": [
      {
        "type": "value",
        "key": "notification_name",
        "value": "keyOperate_info_zr1s"
      }
    ]
  },
  "version": "0.9.43",
  "execution": {
    "id": "dc3e7bba-da5f-4599-93c9-e8cbc1baaa1c",
    "start": 1742610042.0778,
    "end_time": 1742610043.6010861,
    "duration": 1.5232861042022705
  },
  "config": {
    "region": "",
    "regions": [],
    "cache": "~/.cache/cloud-custodian.cache",
    "profile": null,
    "account_id": null,
    "assume_role": null,
    "session_policy": null,
    "external_id": null,
    "log_group": null,
    "tracer": null,
    "metrics_enabled": null,
    "metrics": null,
    "output_dir": ".",
    "cache_period": 0,
    "dryrun": false,
    "authorization_file": null,
    "subparser": "run",
    "config": null,
    "configs": [
      "testNotification/query-filter.yml"
    ],
    "policy_filters": [],
    "resource_types": [],
    "verbose": 1,
    "quiet": null,
    "debug": false,
    "skip_validation": false,
    "command": "c7n.commands.run",
    "vars": null
  },
  "sys-stats": {
    "snapshot_time": 1.5232856273651123,
    "num_fds": 1,
    "cpu_user": 0.010000000000000009,
    "num_ctx_switches_voluntary": 17,
    "num_ctx_switches_involuntary": 38,
    "read_count": 59,
    "write_count": 14,
    "write_bytes": 8192,
    "rss": 782336,
    "vms": 75898880,
    "shared": 208896,
    "data": 8921088
  },
  "api-stats": {},
  "metrics": [
    {
      "MetricName": "ResourceCount",
      "Timestamp": "2025-03-22T10:20:43.600782",
      "Value": 1,
      "Unit": "Count"
    },
    {
      "MetricName": "ResourceTime",
      "Timestamp": "2025-03-22T10:20:43.600802",
      "Value": 1.521139144897461,
      "Unit": "Seconds"
    },
    {
      "MetricName": "ActionTime",
      "Timestamp": "2025-03-22T10:20:43.601077",
      "Value": 1.6689300537109375e-06,
      "Unit": "Seconds"
    }
  ]
}